LICENSE
README.md
pyproject.toml
setup.py
dm_meltingpot.egg-info/PKG-INFO
dm_meltingpot.egg-info/SOURCES.txt
dm_meltingpot.egg-info/dependency_links.txt
dm_meltingpot.egg-info/requires.txt
dm_meltingpot.egg-info/top_level.txt
meltingpot/__init__.py
meltingpot/bot.py
meltingpot/bot_test.py
meltingpot/scenario.py
meltingpot/scenario_test.py
meltingpot/substrate.py
meltingpot/substrate_test.py
meltingpot/configs/__init__.py
meltingpot/configs/bots/__init__.py
meltingpot/configs/bots/bot_configs_test.py
meltingpot/configs/scenarios/__init__.py
meltingpot/configs/scenarios/scenario_configs_test.py
meltingpot/configs/substrates/__init__.py
meltingpot/configs/substrates/allelopathic_harvest.py
meltingpot/configs/substrates/allelopathic_harvest__open.py
meltingpot/configs/substrates/bach_or_stravinsky_in_the_matrix__arena.py
meltingpot/configs/substrates/bach_or_stravinsky_in_the_matrix__repeated.py
meltingpot/configs/substrates/boat_race.py
meltingpot/configs/substrates/boat_race__eight_races.py
meltingpot/configs/substrates/chemistry__three_metabolic_cycles.py
meltingpot/configs/substrates/chemistry__three_metabolic_cycles_with_plentiful_distractors.py
meltingpot/configs/substrates/chemistry__two_metabolic_cycles.py
meltingpot/configs/substrates/chemistry__two_metabolic_cycles_with_distractors.py
meltingpot/configs/substrates/chicken_in_the_matrix__arena.py
meltingpot/configs/substrates/chicken_in_the_matrix__repeated.py
meltingpot/configs/substrates/clean_up.py
meltingpot/configs/substrates/coins.py
meltingpot/configs/substrates/collaborative_cooking.py
meltingpot/configs/substrates/collaborative_cooking__asymmetric.py
meltingpot/configs/substrates/collaborative_cooking__circuit.py
meltingpot/configs/substrates/collaborative_cooking__cramped.py
meltingpot/configs/substrates/collaborative_cooking__crowded.py
meltingpot/configs/substrates/collaborative_cooking__figure_eight.py
meltingpot/configs/substrates/collaborative_cooking__forced.py
meltingpot/configs/substrates/collaborative_cooking__ring.py
meltingpot/configs/substrates/commons_harvest__closed.py
meltingpot/configs/substrates/commons_harvest__open.py
