Metadata-Version: 2.1
Name: dm-meltingpot
Version: 2.4.0
Summary: A suite of test scenarios for multi-agent reinforcement learning.
Home-page: https://github.com/google-deepmind/meltingpot
Download-URL: https://github.com/google-deepmind/meltingpot/releases
Author: DeepMind
Author-email: noreply@google.com
License: Apache 2.0
Keywords: multi-agent reinforcement-learning python machine-learning
Classifier: Development Status :: 4 - Beta
Classifier: Intended Audience :: Developers
Classifier: Intended Audience :: Education
Classifier: Intended Audience :: Science/Research
Classifier: License :: OSI Approved :: Apache Software License
Classifier: Operating System :: POSIX :: Linux
Classifier: Operating System :: MacOS :: MacOS X
Classifier: Programming Language :: Python :: 3 :: Only
Classifier: Programming Language :: Python :: 3.11
Classifier: Programming Language :: Python :: 3.12
Classifier: Programming Language :: Python :: 3.13
Classifier: Topic :: Scientific/Engineering :: Artificial Intelligence
Requires-Python: >=3.11
Provides-Extra: dev
License-File: LICENSE
